flash_card/__init__.py
flash_card/frontend/build/asset-manifest.json
flash_card/frontend/build/bootstrap.min.css
flash_card/frontend/build/index.html
flash_card/frontend/build/static/js/2.c97c516a.chunk.js
flash_card/frontend/build/static/js/2.c97c516a.chunk.js.LICENSE.txt
flash_card/frontend/build/static/js/2.c97c516a.chunk.js.map
flash_card/frontend/build/static/js/main.c8e5baba.chunk.js
flash_card/frontend/build/static/js/main.c8e5baba.chunk.js.map
flash_card/frontend/build/static/js/main.ef61fddc.chunk.js
flash_card/frontend/build/static/js/main.ef61fddc.chunk.js.map
flash_card/frontend/build/static/js/runtime-main.5935c03d.js
flash_card/frontend/build/static/js/runtime-main.5935c03d.js.map
st_flashcard-0.0.5.dist-info/LICENSE
st_flashcard-0.0.5.dist-info/METADATA
st_flashcard-0.0.5.dist-info/WHEEL
st_flashcard-0.0.5.dist-info/top_level.txt
st_flashcard-0.0.5.dist-info/RECORD
