Metadata-Version: 2.1
Name: st-flashcard
Version: 0.0.5
Summary: Custom flash card component for streamlit
Home-page: https://scout.cool
Author: Leejay Xia
Author-email: leejayxia@gmail.com
License: UNKNOWN
Platform: UNKNOWN
Requires-Python: >=3.8
Requires-Dist: streamlit (>=0.86)
